snet.snet_cli-2.1.1-py3.11-nspkg.pth
snet/snet_cli/__init__.py
snet/snet_cli/contract.py
snet/snet_cli/version.py
snet/snet_cli/metadata/__init__.py
snet/snet_cli/metadata/organization.py
snet/snet_cli/metadata/service.py
snet/snet_cli/resources/package.json
snet/snet_cli/resources/root_certificate.py
snet/snet_cli/resources/contracts/abi/MultiPartyEscrow.json
snet/snet_cli/resources/contracts/abi/Registry.json
snet/snet_cli/resources/contracts/abi/SingularityNetToken.json
snet/snet_cli/resources/contracts/networks/MultiPartyEscrow.json
snet/snet_cli/resources/contracts/networks/Registry.json
snet/snet_cli/resources/contracts/networks/SingularityNetToken.json
snet/snet_cli/resources/proto/control_service.proto
snet/snet_cli/resources/proto/control_service_pb2.py
snet/snet_cli/resources/proto/control_service_pb2_grpc.py
snet/snet_cli/resources/proto/merckledag.proto
snet/snet_cli/resources/proto/merckledag_pb2.py
snet/snet_cli/resources/proto/merckledag_pb2_grpc.py
snet/snet_cli/resources/proto/state_service.proto
snet/snet_cli/resources/proto/state_service_pb2.py
snet/snet_cli/resources/proto/state_service_pb2_grpc.py
snet/snet_cli/resources/proto/token_service.proto
snet/snet_cli/resources/proto/token_service_pb2.py
snet/snet_cli/resources/proto/token_service_pb2_grpc.py
snet/snet_cli/resources/proto/training.proto
snet/snet_cli/resources/proto/training_pb2.py
snet/snet_cli/resources/proto/training_pb2_grpc.py
snet/snet_cli/resources/proto/unixfs.proto
snet/snet_cli/resources/proto/unixfs_pb2.py
snet/snet_cli/resources/proto/unixfs_pb2_grpc.py
snet/snet_cli/utils/__init__.py
snet/snet_cli/utils/ipfs_utils.py
snet/snet_cli/utils/proto_utils.py
snet/snet_cli/utils/utils.py
snet_cli/__init__.py
snet_cli/arguments.py
snet_cli/config.py
snet_cli/identity.py
snet_cli/commands/__init__.py
snet_cli/commands/commands.py
snet_cli/commands/mpe_account.py
snet_cli/commands/mpe_channel.py
snet_cli/commands/mpe_client.py
snet_cli/commands/mpe_service.py
snet.snet_cli-2.1.1.dist-info/LICENSE
snet.snet_cli-2.1.1.dist-info/METADATA
snet.snet_cli-2.1.1.dist-info/WHEEL
snet.snet_cli-2.1.1.dist-info/namespace_packages.txt
snet.snet_cli-2.1.1.dist-info/top_level.txt
snet.snet_cli-2.1.1.dist-info/RECORD
