Metadata-Version: 2.1
Name: snet.snet-cli
Version: 2.1.1
Summary: SingularityNET CLI standalone namespace package
Home-page: https://github.com/singnet/snet-cli
Author: SingularityNET Foundation
Author-email: info@singularitynet.io
License: MIT
Requires-Python: >=3.11
License-File: LICENSE
Requires-Dist: protobuf ==4.21.6
Requires-Dist: grpcio-tools ==1.59.0
Requires-Dist: wheel ==0.41.2
Requires-Dist: jsonrpcclient ==4.0.3
Requires-Dist: eth-hash ==0.5.2
Requires-Dist: rlp ==3.0.0
Requires-Dist: eth-rlp ==0.3.0
Requires-Dist: web3 ==6.11.1
Requires-Dist: mnemonic ==0.20
Requires-Dist: pycoin ==0.92.20230326
Requires-Dist: pyyaml ==6.0.1
Requires-Dist: ipfshttpclient ==0.4.13.2
Requires-Dist: rfc3986 ==2.0.0
Requires-Dist: pymultihash ==0.8.2
Requires-Dist: base58 ==2.1.1
Requires-Dist: argcomplete ==3.1.2
Requires-Dist: grpcio-health-checking ==1.59.0
Requires-Dist: jsonschema ==4.0.0
Requires-Dist: eth-account ==0.9.0
